aiops_sdk/__init__.py
aiops_sdk/client.py
aiops_sdk/config.py
aiops_sdk/exceptions.py
aiops_sdk/heartbeat.py
aiops_sdk/logging_hook.py
aiops_sdk/payload.py
aiops_sdk/scheduler.py
aiops_sdk/utils.py
aiops_sdk/version.py
aiops_sdk/integrations/flask.py
aiops_sdk-0.1.5.dist-info/METADATA
aiops_sdk-0.1.5.dist-info/WHEEL
aiops_sdk-0.1.5.dist-info/top_level.txt
aiops_sdk-0.1.5.dist-info/RECORD
