Metadata-Version: 2.4
Name: aiops-sdk
Version: 0.1.5
Summary: Lightweight SDK for AIOps monitoring platform
Author-email: Your Name / Org <you@company.com>
Requires-Python: >=3.8
Requires-Dist: requests
